ngdi/__init__.py
ngdi/config.py
ngdi/engines.py
ngdi/nebula_algo.py
ngdi/nebula_data.py
ngdi/nebula_gnn.py
ngdi/nebula_reader.py
ngdi/nebula_writer.py
ngdi/ngdi_api/__init__.py
ngdi/ngdi_api/__main__.py
ngdi/ngdi_api/app.py
ngdi-0.2.6.dist-info/WHEEL
ngdi-0.2.6.dist-info/METADATA
ngdi-0.2.6.dist-info/licenses/LICENSE
ngdi-0.2.6.dist-info/RECORD
