Metadata-Version: 2.1
Name: ngdi
Version: 0.2.6
Summary: NebulaGraph Data Intelligence Suite
License: Apache-2.0
Author-email: Wey Gu <weyl.gu@gmail.com>
Requires-Python: >=3.6
Requires-Dist: flask>=2.0.3
Requires-Dist: networkx>=2.5.1
Provides-Extra: all
Requires-Dist: ngdi[networkx,spark]; extra == "all"
Provides-Extra: networkx
Requires-Dist: networkx>=2.5.1; extra == "networkx"
Provides-Extra: spark
Requires-Dist: pyspark>=3.2.3; extra == "spark"
